regixtest/__init__.py
regixtest/cli.py
regixtest/data_extensions.py
regixtest/pi2.py
regixtest-0.1.4.dist-info/licenses/LICENSE
regixtest-0.1.4.dist-info/METADATA
regixtest-0.1.4.dist-info/WHEEL
regixtest-0.1.4.dist-info/entry_points.txt
regixtest-0.1.4.dist-info/top_level.txt
regixtest-0.1.4.dist-info/RECORD
