Metadata-Version: 2.4
Name: RegixTest
Version: 0.1.4
Summary: CLI tool to check common file extensions on a target website.
Author-email: TUHIN <tuhin.khan1995@gmail.com>
License-Expression: MIT
Requires-Python: >=3.8
License-File: LICENSE
Requires-Dist: requests>=2.28
Dynamic: license-file
